{
	"name": "relationship-bhzjjxhozp",
	"properties": {
		"Name": "relationship-bhzjjxhozp",
		"EntityType": "RELATIONSHIP",
		"Namespace": {
			"DatabaseName": "Kyndryl_SAP_Supplier_Mapping"
		},
		"Origin": {
			"Type": "SPARK"
		},
		"FromTableName": "Vendor",
		"ToTableName": "PurchaseOrder",
		"ColumnRelationshipInformations": [
			{
				"FromColumnName": "VendorId",
				"ToColumnName": "VendorId"
			}
		],
		"RelationshipType": 0,
		"Properties": {
			"DerivedModelRelationshipInfo": "{\"baseRelationship\":{\"fromEntity\":\"Vendor.cdm.json/Vendor\",\"toEntity\":\"PurchaseOrder.cdm.json/PurchaseOrder\",\"joinPairs\":[{\"fromAttribute\":\"VendorId\",\"toAttribute\":\"VendorId\"}]}}"
		},
		"PublishStatus": "PUBLISHED",
		"ObjectVersion": 1,
		"ObjectId": "28922072-04a0-462d-b1f7-4911842f803b"
	},
	"type": "RELATIONSHIP"
}