{
	"name": "relationship-pyfdkurspe",
	"properties": {
		"Name": "relationship-pyfdkurspe",
		"EntityType": "RELATIONSHIP",
		"Namespace": {
			"DatabaseName": "ConsumerGoods_vfz"
		},
		"Origin": {
			"Type": "SPARK"
		},
		"FromTableName": "Party",
		"ToTableName": "PartyRole",
		"ColumnRelationshipInformations": [
			{
				"FromColumnName": "PartyId",
				"ToColumnName": "PartyId"
			}
		],
		"RelationshipType": 0,
		"Properties": {
			"DerivedModelRelationshipInfo": "{\"baseRelationship\":{\"fromEntity\":\"Party.cdm.json/Party\",\"toEntity\":\"PartyRole.cdm.json/PartyRole\",\"joinPairs\":[{\"fromAttribute\":\"PartyId\",\"toAttribute\":\"PartyId\"}]}}"
		},
		"PublishStatus": "PUBLISHED",
		"ObjectVersion": 1,
		"ObjectId": "000c1fb8-0ba3-4ec5-83d7-cb01d100fe4a"
	},
	"type": "RELATIONSHIP"
}