{
	"name": "relationship-cwrjiuyjgy",
	"properties": {
		"Name": "relationship-cwrjiuyjgy",
		"EntityType": "RELATIONSHIP",
		"Namespace": {
			"DatabaseName": "ConsumerGoods_vfz"
		},
		"Origin": {
			"Type": "SPARK"
		},
		"FromTableName": "QuestionSubject",
		"ToTableName": "Question",
		"ColumnRelationshipInformations": [
			{
				"FromColumnName": "QuestionSubjectId",
				"ToColumnName": "QuestionSubjectId"
			}
		],
		"RelationshipType": 0,
		"Properties": {
			"DerivedModelRelationshipInfo": "{\"baseRelationship\":{\"fromEntity\":\"QuestionSubject.cdm.json/QuestionSubject\",\"toEntity\":\"Question.cdm.json/Question\",\"joinPairs\":[{\"fromAttribute\":\"QuestionSubjectId\",\"toAttribute\":\"QuestionSubjectId\"}]}}"
		},
		"PublishStatus": "PUBLISHED",
		"ObjectVersion": 1,
		"ObjectId": "cf160165-5967-4cbc-9d45-04abded225ab"
	},
	"type": "RELATIONSHIP"
}