{
	"name": "relationship-hofwmpkswp",
	"properties": {
		"Name": "relationship-hofwmpkswp",
		"EntityType": "RELATIONSHIP",
		"Namespace": {
			"DatabaseName": "ConsumerGoods_vfz"
		},
		"Origin": {
			"Type": "SPARK"
		},
		"FromTableName": "Party",
		"ToTableName": "PartyLocationGeographicCriteria",
		"ColumnRelationshipInformations": [
			{
				"FromColumnName": "PartyId",
				"ToColumnName": "PartyId"
			}
		],
		"RelationshipType": 0,
		"Properties": {
			"DerivedModelRelationshipInfo": "{\"baseRelationship\":{\"fromEntity\":\"Party.cdm.json/Party\",\"toEntity\":\"PartyLocationGeographicCriteria.cdm.json/PartyLocationGeographicCriteria\",\"joinPairs\":[{\"fromAttribute\":\"PartyId\",\"toAttribute\":\"PartyId\"}]}}"
		},
		"PublishStatus": "PUBLISHED",
		"ObjectVersion": 1,
		"ObjectId": "2e4e9b4a-a076-4dc2-b712-170abe816186"
	},
	"type": "RELATIONSHIP"
}