{
	"name": "relationship-xgavtysvet",
	"properties": {
		"Name": "relationship-xgavtysvet",
		"EntityType": "RELATIONSHIP",
		"Namespace": {
			"DatabaseName": "ConsumerGoods_vfz"
		},
		"Origin": {
			"Type": "SPARK"
		},
		"FromTableName": "Party",
		"ToTableName": "Customer",
		"ColumnRelationshipInformations": [
			{
				"FromColumnName": "PartyId",
				"ToColumnName": "PartyId"
			}
		],
		"RelationshipType": 0,
		"Properties": {
			"DerivedModelRelationshipInfo": "{\"baseRelationship\":{\"fromEntity\":\"Party.cdm.json/Party\",\"toEntity\":\"Customer.cdm.json/Customer\",\"joinPairs\":[{\"fromAttribute\":\"PartyId\",\"toAttribute\":\"PartyId\"}]}}"
		},
		"PublishStatus": "PUBLISHED",
		"ObjectVersion": 2,
		"ObjectId": "53bdf35a-6b08-464f-b8d7-867475504c10"
	},
	"type": "RELATIONSHIP"
}