{
	"name": "relationship-qxabppxiye",
	"properties": {
		"Name": "relationship-qxabppxiye",
		"EntityType": "RELATIONSHIP",
		"Namespace": {
			"DatabaseName": "ConsumerGoods_vfz"
		},
		"Origin": {
			"Type": "SPARK"
		},
		"FromTableName": "Party",
		"ToTableName": "PartyRoleEvent",
		"ColumnRelationshipInformations": [
			{
				"FromColumnName": "PartyId",
				"ToColumnName": "PartyId"
			}
		],
		"RelationshipType": 0,
		"Properties": {
			"DerivedModelRelationshipInfo": "{\"baseRelationship\":{\"fromEntity\":\"Party.cdm.json/Party\",\"toEntity\":\"PartyRoleEvent.cdm.json/PartyRoleEvent\",\"joinPairs\":[{\"fromAttribute\":\"PartyId\",\"toAttribute\":\"PartyId\"}]}}"
		},
		"PublishStatus": "PUBLISHED",
		"ObjectVersion": 1,
		"ObjectId": "d71a8c12-9a68-4b4d-92d1-795617418ef3"
	},
	"type": "RELATIONSHIP"
}