{
	"name": "relationship-hwrdvnkaga",
	"properties": {
		"Name": "relationship-hwrdvnkaga",
		"EntityType": "RELATIONSHIP",
		"Namespace": {
			"DatabaseName": "ConsumerGoods_vfz"
		},
		"Origin": {
			"Type": "SPARK"
		},
		"FromTableName": "Contract",
		"ToTableName": "JointMarketingAgreement",
		"ColumnRelationshipInformations": [
			{
				"FromColumnName": "ContractId",
				"ToColumnName": "ContractId"
			}
		],
		"RelationshipType": 0,
		"Properties": {
			"DerivedModelRelationshipInfo": "{\"baseRelationship\":{\"fromEntity\":\"Contract.cdm.json/Contract\",\"toEntity\":\"JointMarketingAgreement.cdm.json/JointMarketingAgreement\",\"joinPairs\":[{\"fromAttribute\":\"ContractId\",\"toAttribute\":\"ContractId\"}]}}"
		},
		"PublishStatus": "PUBLISHED",
		"ObjectVersion": 1,
		"ObjectId": "3fe2d969-a2f3-4b00-afa8-887d16c956f2"
	},
	"type": "RELATIONSHIP"
}